lkeb_progress/__init__.py
lkeb_progress/progress.py
lkeb_progress-0.2.0.dist-info/METADATA
lkeb_progress-0.2.0.dist-info/WHEEL
lkeb_progress-0.2.0.dist-info/RECORD
