Metadata-Version: 2.4
Name: lkeb_progress
Version: 0.2.0
Summary: Progressbar based on Rich
Author-email: Patrick de Koning <pjhdekoning@lumc.nl>
Keywords: Rich
Classifier: Operating System :: OS Independent
Classifier: Programming Language :: Python :: 3
Requires-Python: >=3.9
Requires-Dist: rich
